soundstimbuilder/__init__.py
soundstimbuilder/_version.py
soundstimbuilder/snd.py
soundstimbuilder/snddict.py
soundstimbuilder/sndfactory.py
soundstimbuilder/sndseq.py
soundstimbuilder/utils.py
soundstimbuilder/praattextgrids/__init__.py
soundstimbuilder/praattextgrids/templates.py
soundstimbuilder/praattextgrids/transcript.py
soundstimbuilder/tests/__init__.py
soundstimbuilder/tests/test_snd.py
soundstimbuilder-0.1.0.data/data/LICENSE
soundstimbuilder-0.1.0.dist-info/LICENSE
soundstimbuilder-0.1.0.dist-info/METADATA
soundstimbuilder-0.1.0.dist-info/WHEEL
soundstimbuilder-0.1.0.dist-info/top_level.txt
soundstimbuilder-0.1.0.dist-info/RECORD
