Metadata-Version: 2.1
Name: soundstimbuilder
Version: 0.1.0
Summary: A package to create experimental sound stimuli
Home-page: https://github.com/gbeckers/soundstimbuilder
Author: Gabriel J.L. Beckers
Author-email: gabriel@gbeckers.nl
License: BSD-3
Project-URL: Source, https://github.com/gbeckers/soundstimbuilder
Platform: UNKNOWN
Classifier: Programming Language :: Python :: 3
Classifier: Programming Language :: Python :: 3.6
Classifier: Programming Language :: Python :: 3.7
Classifier: Programming Language :: Python :: 3.8
Classifier: License :: OSI Approved :: BSD License
Classifier: Operating System :: OS Independent
Classifier: Development Status :: 3 - Alpha
Classifier: Intended Audience :: Education
Classifier: Intended Audience :: Developers
Classifier: Intended Audience :: Information Technology
Classifier: Intended Audience :: Science/Research
Requires-Python: >=3.6
Requires-Dist: numpy
